{"﻿language.code":"ko-KR","language":"한국어","staxel.onScreenGuide.BefriendingVillagers":"","staxel.onScreenGuide.BefriendingVillagers.1":"","staxel.onScreenGuide.BefriendingVillagers.2":"","staxel.onScreenGuide.BefriendingVillagers.3":"","staxel.onScreenGuide.BefriendingVillagers.4":"","staxel.onScreenGuide.BuyingAndSelling":"","staxel.onScreenGuide.BuyingAndSelling.1":"","staxel.onScreenGuide.BuyingAndSelling.2":"","staxel.onScreenGuide.Catalogue":"","staxel.onScreenGuide.Catalogue.1":"","staxel.onScreenGuide.Catalogue.2":"","staxel.onScreenGuide.Catalogue.3":"","staxel.onScreenGuide.Catalogue.4":"","staxel.onScreenGuide.CatchingBugs":"","staxel.onScreenGuide.CatchingBugs.1":"","staxel.onScreenGuide.CatchingBugs.2":"","staxel.onScreenGuide.Cooking":"","staxel.onScreenGuide.Cooking.1":"","staxel.onScreenGuide.Cooking.2":"","staxel.onScreenGuide.Cooking.3":"","staxel.onScreenGuide.Cooking.4":"","staxel.onScreenGuide.Cooking.5":"","staxel.onScreenGuide.Cooking.6":"","staxel.onScreenGuide.Cooking.7":"","staxel.onScreenGuide.CowCare":"","staxel.onScreenGuide.CowCare.1":"","staxel.onScreenGuide.CowCare.2":"","staxel.onScreenGuide.CowCare.3":"","staxel.onScreenGuide.CowCare.4":"","staxel.onScreenGuide.Crafting":"","staxel.onScreenGuide.Crafting.1":"","staxel.onScreenGuide.Crafting.2":"","staxel.onScreenGuide.Crafting.3":"","staxel.onScreenGuide.Crafting.4":"","staxel.onScreenGuide.Crafting.5":"","staxel.onScreenGuide.Crafting.6":"","staxel.onScreenGuide.Crafting.7":"","staxel.onScreenGuide.Fishing":"","staxel.onScreenGuide.Fishing.1":"","staxel.onScreenGuide.Fishing.2":"","staxel.onScreenGuide.Fishing.3":"","staxel.onScreenGuide.GettingStarted":"","staxel.onScreenGuide.GettingStarted.1":"","staxel.onScreenGuide.GettingStarted.2":"","staxel.onScreenGuide.GettingStarted.3":"","staxel.onScreenGuide.GrowingCrops":"","staxel.onScreenGuide.GrowingCrops.1":"","staxel.onScreenGuide.GrowingCrops.2":"","staxel.onScreenGuide.GrowingCrops.3":"","staxel.onScreenGuide.GrowingCrops.4":"","staxel.onScreenGuide.MarkerProtection":"","staxel.onScreenGuide.MarkerProtection.1":"","staxel.onScreenGuide.MarkerProtection.2":"","staxel.onScreenGuide.MarkerProtection.3":"","staxel.onScreenGuide.MarkerProtection.4":"","staxel.onScreenGuide.MarkerProtection.5":"","staxel.onScreenGuide.MarkerProtection.6":"","staxel.onScreenGuide.Markers":"","staxel.onScreenGuide.Markers.1":"","staxel.onScreenGuide.Markers.2":"","staxel.onScreenGuide.Markers.3":"","staxel.onScreenGuide.Markers.4":"","staxel.onScreenGuide.Markers.5":"","staxel.onScreenGuide.Markers.6":"","staxel.onScreenGuides.Title":""}